README.md
setup.py
MOMORING/__init__.py
MOMORING.egg-info/PKG-INFO
MOMORING.egg-info/SOURCES.txt
MOMORING.egg-info/dependency_links.txt
MOMORING.egg-info/entry_points.txt
MOMORING.egg-info/requires.txt
MOMORING.egg-info/top_level.txt
MOMORING/api/__init__.py
MOMORING/api/create_project.py
MOMORING/applications/__init__.py
MOMORING/applications/cmd.py
MOMORING/modules/__init__.py
MOMORING/modules/create.py
MOMORING/modules/files/__init__.py
MOMORING/modules/files/applications_init_template.py
MOMORING/modules/files/applications_template.py
MOMORING/modules/files/git_ignore_template.py
MOMORING/modules/files/main_template.py
MOMORING/modules/files/nitrogen_utils.py
MOMORING/modules/files/readme_template.py
MOMORING/utils/__init__.py