Metadata-Version: 2.1
Name: MOMORING
Version: 1.4.2
Summary: A simple, graceful tool for developer
Author: Masgils
Author-email: masgils@foxmail.com
